setup.py
waiterdb/__init__.py
waiterdb/connection.py
waiterdb/cursor.py
waiterdb/errors.py
waiterdb/types.py
waiterdb.egg-info/PKG-INFO
waiterdb.egg-info/SOURCES.txt
waiterdb.egg-info/dependency_links.txt
waiterdb.egg-info/top_level.txt
waiterdb.egg-info/zip-safe
waiterdb/avatica/__init__.py
waiterdb/avatica/client.py
waiterdb/avatica/__init__.py
waiterdb/avatica/client.py