Metadata-Version: 1.1
Name: waiterdb
Version: 1.0.5
Summary: waiter python client.
Home-page: UNKNOWN
Author: zhujiajunup
Author-email: zhujiajunup@163.com
License: MIT
Keywords: waiter python package
Platform: UNKNOWN
Classifier: License :: OSI Approved :: MIT License
Classifier: Programming Language :: Python
Classifier: Intended Audience :: Developers
Classifier: Operating System :: OS Independent
Classifier: Programming Language :: Python :: 3
